deep_rl/__init__.py
deep_rl/configuration.py
deep_rl/core.py
deep_rl/core_test.py
deep_rl/registry.py
deep_rl/testing.py
deep_rl/utils.py
deep_rl/actor_critic/__init__.py
deep_rl/actor_critic/a2c.py
deep_rl/actor_critic/a3c.py
deep_rl/actor_critic/acktr.py
deep_rl/actor_critic/agent.py
deep_rl/actor_critic/environment.py
deep_rl/actor_critic/model.py
deep_rl/actor_critic/ppo.py
deep_rl/actor_critic/unreal/__init__.py
deep_rl/actor_critic/unreal/storage.py
deep_rl/actor_critic/unreal/unreal.py
deep_rl/actor_critic/unreal/unreal_ppo.py
deep_rl/actor_critic/unreal/utils.py
deep_rl/common/__init__.py
deep_rl/common/console_util.py
deep_rl/common/env.py
deep_rl/common/metrics.py
deep_rl/common/metrics_test.py
deep_rl/common/multiprocessing.py
deep_rl/common/pytorch.py
deep_rl/common/schedules.py
deep_rl/common/segment_tree.py
deep_rl/common/storage.py
deep_rl/common/storage_test.py
deep_rl/common/tensorflow_summary.py
deep_rl/common/torchsummary.py
deep_rl/common/train_wrappers.py
deep_rl/common/util.py
deep_rl/common/vec_env.py
deep_rl/deepq/__init__.py
deep_rl/deepq/dqn.py
deep_rl/deepq/replay.py
deep_rl/deepq/util.py
deep_rl/model/__init__.py
deep_rl/model/model.py
deep_rl/model/module.py
deep_rl/optim/__init__.py
deep_rl/optim/kfac.py
deep_rl/optim/shared_adam.py
deep_rl/optim/shared_rmsprop.py
deep_rl-0.3.7.dist-info/LICENSE
deep_rl-0.3.7.dist-info/METADATA
deep_rl-0.3.7.dist-info/WHEEL
deep_rl-0.3.7.dist-info/top_level.txt
deep_rl-0.3.7.dist-info/RECORD
