Metadata-Version: 2.1
Name: deep-rl
Version: 0.3.7
Summary: UNKNOWN
Home-page: UNKNOWN
Author: Jonáš Kulhánek
Author-email: jonas.kulhanek@live.com
License: MIT License
Platform: UNKNOWN
Requires-Dist: matplotlib
Requires-Dist: numpy
Requires-Dist: torch
Requires-Dist: gym
